Metadata-Version: 2.1
Name: minterpy-levelsets
Version: 0.1.0
Summary: Levelset extensions for the minterpy library
Home-page: https://codebase.helmholtz.cloud/interpol/minterpy-levelsets
Author: file: AUTHORS.md
Author-email: Sachin Krishnan Thekke Veettil <sthekke@mpi-cbg.de>
Maintainer: Sachin Krishnan Thekke Veettil
Maintainer-email: sthekke@mpi-cbg.de
License: MIT
Project-URL: Homepage, https://codebase.helmholtz.cloud/interpol/minterpy-levelsets
Project-URL: Bug Tracker, https://codebase.helmholtz.cloud/interpol/minterpy-levelsets/-/issues
Platform: Any
Classifier: Programming Language :: Python :: 3
Classifier: Development Status :: 1 - Planning
Classifier: License :: OSI Approved :: MIT License
Classifier: Operating System :: OS Independent
Classifier: Intended Audience :: Science/Research
Requires-Python: >=3.7
License-File: LICENSE
License-File: AUTHORS.md
